{
  "type": "object",
  "additionalProperties": false,
  "required": [
    "gates"
  ],
  "properties": {
    "parameters": {
      "type": "array",
      "items": {
        "type": "object",
        "additionalProperties": false,
        "required": [
          "name",
          "type"
        ],
        "properties": {
          "name": {
            "type": "string"
          },
          "type": {
            "type": "string",
            "pattern": "(\\bstring\\b|\\bnumber\\b|\\bboolean\\b|\\barray\\b)"
          },
          "default": {
            "anyOf": [
              {
                "type": "string"
              },
              {
                "type": "number"
              },
              {
                "type": "boolean"
              },
              {
                "type": "array",
                "items": {
                  "anyOf": [
                    {
                      "type": "string"
                    },
                    {
                      "type": "number"
                    },
                    {
                      "type": "boolean"
                    }
                  ]
                }
              }
            ]
          },
          "values": {
            "type": "array",
            "items": {
              "anyOf": [
                {
                  "type": "string"
                },
                {
                  "type": "number"
                },
                {
                  "type": "boolean"
                }
              ]
            }
          }
        },
        "dependencies": {
          "values": {
            "properties": {
              "type": {
                "type": "string",
                "pattern": "\\barray\\b"
              }
            },
            "required": [
              "type"
            ]
          }
        }
      }
    },
    "version": {
      "type": "string"
    },
    "name": {
      "type": "string"
    },
    "gates": {
      "type": "array",
      "items": {
        "type": "object",
        "additionalProperties": false,
        "required": [
          "name",
          "rule"
        ],
        "properties": {
          "name": {
            "type": "string"
          },
          "rule": {
            "type": "array",
            "items": {
              "type": "string"
            }
          },
          "notify-on-fail": {
            "type": "array",
            "items": {
              "type": "object",
              "additionalProperties": false,
              "required": [
                "type"
              ],
              "properties": {
                "type": {
                  "type": "string",
                  "pattern": "(\\bemail\\b|\\bwework-message\\b)"
                },
                "receivers": {
                  "anyOf": [
                    {
                      "type": "array",
                      "items": {
                        "type": "string"
                      }
                    },
                    {
                      "type": "string"
                    }
                  ]
                }
              }
            }
          }
        }
      }
    }
  }
}
